{
  "hints": [],
  "groups": [
    {
      "sourceType": "com.zlpay.rabbitmq.properties.RabbitmqProperties",
      "name": "spring.rabbitmq",
      "type": "com.zlpay.rabbitmq.properties.RabbitmqProperties"
    }
  ],
  "properties": [
    {
      "sourceType": "com.zlpay.rabbitmq.properties.RabbitmqProperties",
      "name": "spring.rabbitmq.addresses",
      "description": "队列地址",
      "type": "java.lang.String"
    },
    {
      "sourceType": "com.zlpay.rabbitmq.properties.RabbitmqProperties",
      "name": "spring.rabbitmq.listener-direct-acknowledge-mode",
      "description": "消费消息确认模式",
      "type": "java.lang.String"
    },
    {
      "sourceType": "com.zlpay.rabbitmq.properties.RabbitmqProperties",
      "name": "spring.rabbitmq.password",
      "description": "密码",
      "type": "java.lang.String"
    },
    {
      "sourceType": "com.zlpay.rabbitmq.properties.RabbitmqProperties",
      "name": "spring.rabbitmq.publisher-confirms",
      "description": "消息确认",
      "type": "java.lang.Boolean"
    },
    {
      "sourceType": "com.zlpay.rabbitmq.properties.RabbitmqProperties",
      "name": "spring.rabbitmq.publisher-returns",
      "description": "消息回调",
      "type": "java.lang.Boolean"
    },
    {
      "sourceType": "com.zlpay.rabbitmq.properties.RabbitmqProperties",
      "name": "spring.rabbitmq.template-mandatory",
      "description": "mandatory标志位,只有为true,消息回调才会生效",
      "type": "java.lang.Boolean"
    },
    {
      "sourceType": "com.zlpay.rabbitmq.properties.RabbitmqProperties",
      "name": "spring.rabbitmq.username",
      "description": "用户名",
      "type": "java.lang.String"
    },
    {
      "sourceType": "com.zlpay.rabbitmq.properties.RabbitmqProperties",
      "name": "spring.rabbitmq.virtual-host",
      "description": "虚拟机",
      "type": "java.lang.String"
    }
  ]
}